ns_nornir_table_inventory/__init__.py
ns_nornir_table_inventory/plugins/inventory/__init__.py
ns_nornir_table_inventory/plugins/inventory/table.py
ns_nornir_table_inventory-0.0.1.dist-info/LICENSE
ns_nornir_table_inventory-0.0.1.dist-info/METADATA
ns_nornir_table_inventory-0.0.1.dist-info/WHEEL
ns_nornir_table_inventory-0.0.1.dist-info/entry_points.txt
ns_nornir_table_inventory-0.0.1.dist-info/RECORD
