Metadata-Version: 2.3
Name: ns_nornir_table_inventory
Version: 0.0.1
Summary: nornir inventory plugin,support managing inventory by csv or excel file
License: Apache-2.0
Keywords: nornir,table,csv,excel,inventory
Author: nstamoul
Author-email: nstamoul0@gmail.com
Requires-Python: >=3.7
Classifier: License :: OSI Approved :: Apache Software License
Classifier: Programming Language :: Python :: 3
Classifier: Programming Language :: Python :: 3.7
Classifier: Programming Language :: Python :: 3.8
Classifier: Programming Language :: Python :: 3.9
Classifier: Programming Language :: Python :: 3.10
Classifier: Programming Language :: Python :: 3.11
Classifier: Programming Language :: Python :: 3.12
Classifier: Programming Language :: Python :: 3.13
Classifier: Programming Language :: Python :: 3.6
Classifier: Topic :: System :: Networking
Requires-Dist: nornir (>=3.0.0)
Requires-Dist: pandas (>=1.2.0)
Project-URL: Homepage, https://github.com/nstamoul/ns_nornir_table_inventory
Project-URL: Repository, https://github.com/nstamoul/ns_nornir_table_inventory
